ftb_quest_localizer/__init__.py
ftb_quest_localizer/cli.py
ftb_quest_localizer/localizer.py
ftb_quest_localizer-1.0.2.dist-info/licenses/LICENSE
ftb_quest_localizer-1.0.2.dist-info/METADATA
ftb_quest_localizer-1.0.2.dist-info/WHEEL
ftb_quest_localizer-1.0.2.dist-info/entry_points.txt
ftb_quest_localizer-1.0.2.dist-info/top_level.txt
ftb_quest_localizer-1.0.2.dist-info/RECORD
