Metadata-Version: 2.4
Name: ftb-quest-localizer
Version: 1.0.2
Summary: FTB Quest Localization Helper
Home-page: https://github.com/zack-zzq/FTBQuestLocalizerPython
Author: Zack Zhu
License: MIT
Project-URL: Bug Tracker, https://github.com/zack-zzq/FTBQuestLocalizerPython/issues
Classifier: Programming Language :: Python :: 3
Classifier: Operating System :: OS Independent
Requires-Python: >=3.6
License-File: LICENSE
Requires-Dist: prompt_toolkit>=3.0.0
Dynamic: author
Dynamic: classifier
Dynamic: description
Dynamic: description-content-type
Dynamic: home-page
Dynamic: license
Dynamic: license-file
Dynamic: project-url
Dynamic: requires-dist
Dynamic: requires-python
Dynamic: summary
